boom/__init__.py
boom/_boom.py
boom/bootloader.py
boom/cache.py
boom/command.py
boom/config.py
boom/hostprofile.py
boom/legacy.py
boom/lvm2.py
boom/mounts.py
boom/osprofile.py
boom/py.typed
boom/report.py
boom/stratis.py
boom_boot-1.6.7.data/scripts/boom
boom_boot-1.6.7.dist-info/licenses/LICENSE
boom_boot-1.6.7.dist-info/METADATA
boom_boot-1.6.7.dist-info/WHEEL
boom_boot-1.6.7.dist-info/top_level.txt
boom_boot-1.6.7.dist-info/RECORD
