Metadata-Version: 2.4
Name: boom_boot
Version: 1.6.7
Summary: The Boom Boot Manager
Home-page: https://github.com/snapshotmanager/boom
Author: Bryn M. Reeves
Author-email: "Bryn M. Reeves" <bmr@redhat.com>
License: "Apache-2.0"
Project-URL: Homepage, https://github.com/snapshotmanager/boom-boot
Project-URL: Issues, https://github.com/snapshotmanager/boom-boot/issues
Platform: Linux
Classifier: Development Status :: 5 - Production/Stable
Classifier: Intended Audience :: Developers
Classifier: Intended Audience :: System Administrators
Classifier: Programming Language :: Python
Classifier: Programming Language :: Python :: 3
Classifier: Programming Language :: Python :: Implementation :: CPython
Requires-Python: >=3.6
License-File: LICENSE
Requires-Dist: dbus-python>=1.2.16
Provides-Extra: docs
Requires-Dist: Sphinx>=1.8; extra == "docs"
Dynamic: license-file
